{
  "updatedAt": "2026-07-14T17:10:31.258Z",
  "daily": {
    "ok": true,
    "lastUpdate": "2026.07.14 18:13",
    "period": "7월 1일 ~ 14일",
    "todayRevenue": 46530000,
    "monthRevenue": 700000000,
    "ytdRevenue": 12030000000,
    "monthForecast": 1550000000,
    "top5": [
      {
        "brand": "한독 테라큐민",
        "name": "한독 테라큐민 맥스 60",
        "dailyRevenue": 7810000,
        "dailyQty": 329
      },
      {
        "brand": "YDY뉴트리션",
        "name": "폴라초임계오메가3",
        "dailyRevenue": 4150000,
        "dailyQty": 172
      },
      {
        "brand": "YDY뉴트리션",
        "name": "유한 YDY 혈당케어 여주",
        "dailyRevenue": 3910000,
        "dailyQty": 86
      },
      {
        "brand": "YDY뉴트리션",
        "name": "액티브비큐텐",
        "dailyRevenue": 3350000,
        "dailyQty": 134
      },
      {
        "brand": "YDY뉴트리션",
        "name": "액티브헴철",
        "dailyRevenue": 3260000,
        "dailyQty": 120
      }
    ]
  },
  "weekly": {
    "ok": true,
    "baseDate": "2026년 7월 8일",
    "weekLabel": "2026년 28주차",
    "pbMonthShipment": 462000000,
    "pbYtdShipment": 21060000000,
    "gbMonth": 1760000000,
    "gbYtd": 43770000000,
    "targetAchievement": "65.2%",
    "annualTarget": 75000000000,
    "annualAchievement": "0.3%",
    "period": "2026년 누적"
  },
  "stock": {
    "ok": true,
    "urgentOrder": 1,
    "reviewOrder": 0,
    "inProgress": 43,
    "expiry6m": 0,
    "expiry9m": 0,
    "expiryWithin9m": 0,
    "expiry6to9m": null,
    "expiry9to12m": null,
    "totalAmount": 0,
    "skuCount": 44
  },
  "voc": {
    "ok": true,
    "total": 38,
    "pending": 0,
    "high": 9,
    "completed": 37,
    "processingRate": 97
  }
}
